{
  "doc_id": "39b1ef93c8a2bc10",
  "legacy_doc_id": "0f3aec5f8525",
  "filename": "SST_GLO_SST_L4_REP_OBSERVATIONS_010_024_QUID.pdf",
  "filepath": "docs/copernicus_docs/QUID/SST_GLO_SST_L4_REP_OBSERVATIONS_010_024_QUID.pdf",
  "extension": ".pdf",
  "file_size_mb": 0.52,
  "pages": 14,
  "text_preview": " \n  \nSST TAC Production Centre  \n \n \nCopernicus Climate Change ServiceL4 SST/IST analyses \n    \nEuropean Space Agency Sea Surface Temperature \nClimate Change Initiative L4 SST analyses \n \nSST-GLO-SST-L4-REP-OBSERVATIONS-010-024 \n Issue: 5.0 \nContributors: I. Karagali, S. Good. \nApproval date by the CMEMS product quality coordination team: 24/02/2026 \n \n \n \n \n  \n\nProducts \nSST-GLO-SST-L4-REP-OBSERVATIONS-010-024 \nRef: \nDate: \nIssue: \nCMEMS-SST-QUID-010-024 \n12 November 2025 \n5.0 \n \n                                                      Page 2/ 14 \nCHANGE RECORD \n \nWhen the quality of the products changes, the QuID is updated, and a row is added to this table.   \nThe third column specifies which sections or sub-sections have been updated.  The fourth column should \nmention the reason for updating the document . Column 5 should include the names of the author (s) \ndoing the changes. Including the name in column 6 shows that the document has been validated by the \nTAC/MFC PQ leader or deputy (or TAC/MFC PQ leader or the deputy). This validation means th e \ndocument was checked for contents, formats and consistency with other documents. \n \nIssue Date § Description of Change Author Validated By \n1.0 January \n2017 All Creation of the \ndocument \nSimon Good  \n1.1 March \n2017  \nResponses to review; \naddition of logos and \nlicensing information. \nSimon Good  \n2.0 12 April \n2019 All \nUpdate ESA SST CCI \nanalyses to version \nCDR2.0 \nSimon Good  \n2.1 \n10 \nSeptember \n2019 \n Added C3S ICDR2.0 \nSimon Good Mercator Ocean \n2.2 \n10 \nSeptember \n2020 \n Extension to 2019 and \nupstream data change \nSimon Good Bruno Buongiorno Nardelli \n2.3 15 January \n2021 II Temporal extensions Simon Good Bruno Buongiorno Nardelli \n3.0 3 October \n2024 All Replacement product Ioanna Karagali A. Pisano \n4.0 18 July \n2025  \nReintroduced dataset \nESACCI-GLO-SST-L4-REP-\nOBS-SST \nSimon Good A. Pisano \n5.0 \n12 \nNovember \n2025 \nAll \nNew document template \nand u pdate ESA SST CCI \nanalyses to version \nCDR3.0 \nSimon Good A. Pisano \n \n \n \n  \nProducts \nSST-GLO-SST-L4-REP-OBSERVATIONS-010-024 \nRef: \nDate: \nIssue: \nCMEMS-SST-QUID-010-024 \n12 November 2025 \n5.0 \n \n                                                      Page 3/ 14 \nACRONYM TABLE \nAcronym Description \n(A)ATSR (Advanced) Along Track Scanning Radiometer \nAASTI Arctic and Antarctic Surface Temperatures from thermal Infrared \nsatellite radiometers \nAMSR Advanced Microwave Scanning Radiometer \nArgo Array for Real -Time Geostrophic Oceanography . International \nprogram that measures water properties across the world’s ocean \nusing a fleet of robotic instruments that drift with the ocean currents \nand move up and down between the surface and a mid-water level \nAVHRR Advanced Very-High Resolution Radiometer \nC3S Copernicus Climate Change Service \nCCI Climate Change Initiative \nCDR Climate Data Record \nDMI Danish Meteorological Institute \nEAN Estimated Accuracy Number \nESA European Space Agency \nICDR Interim Climate Data Record \nIST Ice Surface Temperature \nMAD Median Absolute Deviation \nOSTIA Operational Sea Surface Temperature and Ice Analysis \nOI Optimal Interpolation \nRSD Robust Standard Deviation \nSLSTR Sea and Land Surface Temperature Radiometer \nSST Sea Surface Temperature \nT2m Temperature at 2m height \nTAC Copernicus Marine Service Thematic Assembly Centre \n \nKEY DEFINITIONS \nFoundation SST The SST from which the diurnal cycle grows each day1 \nMAD Median absolute deviation from the median \nRobust standard \ndeviation (RSD) \n1.4826 × MAD \n \n1 https://www.ghrsst.org/ghrsst-data-services/for-sst-data-users/products/#section5 \nProducts \nSST-GLO-SST-L4-REP-OBSERVATIONS-010-024 \nRef: \nDate: \nIssue: \nCMEMS-SST-QUID-010-024 \n12 November 2025 \n5.0 \n \n                                                      Page 4/ 14 \nRELEVANT DOCUMENT LIST \nRD.1 Karagali, I. et al. (2024). Global L4 Sea and Sea Ice Surface Temperature Climate Data \nRecord, Version 1.0: Product User Guide and Specifications. Copernicus Climate Change \nService. Document ref. C3S2-312b_WP1-FDDP-SST/IST_2024_PUGS_v1.X2 \nRD.2 Karagali, I. et al. (2024). Global L4 Sea and Sea Ice Surface Temperature Climate Data \nRecord, Version 1.0: Algorithm Theoretical Basis Document. Copernicus Climate Change \nService. Document ref. C3S2-312b_WP1-FDDP-SST/IST_2024_ATBD_v1.X3 \nRD.3 Karagali, I. et al. (2024). Global L4 Sea and Sea Ice Surface Temperature Climate Data \nRecord, Version 1.0: Product Quality Assurance Document. Copernicus Climate Change \nService. Document ref. C3S2-312b_WP1-PDDP-SST/IST_2024_PQAD_v1.2 \nRD.4 Karagali, I. et al. (2024). Global L4 Sea and Sea Ice Surface Temperature Climate Data \nRecord, Version 1.0: Product Quality Assessment Report. Copernicus Climate Change \nService. Document ref. C3S2-312b_WP1-FDDP-SST/IST_2024_PQAR_v1.X4 \nRD.5 ESA SST CCI Product User Guide \n(https://climate.esa.int/media/documents/SST_CCI_D4.2_PUG_v1.1.pdf ) \nRD.6 ESA SST CCI Product Validation and Intercomparison Report \n(https://climate.esa.int/media/documents/SST",
  "extraction_method": "pypdf",
  "extraction_error": null,
  "catalog_entry": {
    "doc_type": "dataset_description",
    "relevance_score": 1.0,
    "summary": "This document is a product user guide and quality information document for the Copernicus Climate Change Service's Level 4 Sea Surface Temperature (SST) analysis, version SST-GLO-SST-L4-REP-OBSERVATIONS-010-024, detailing changes and updates to the product since its creation in January 2017.",
    "provider": {
      "provider_id": "cmems",
      "name": "Copernicus Marine Service Thematic Assembly Centre"
    },
    "product_line": {
      "product_id": "SST-GLO-SST-L4-REP-OBSERVATIONS-010-024",
      "name": "Global L4 Sea Surface Temperature Analysis",
      "model_name": null,
      "region": "Global",
      "product_types": [
        "observation"
      ],
      "categories": [
        "ocean_physics"
      ]
    },
    "datasets": [
      {
        "dataset_id": null,
        "temporal_resolution": "P1D",
        "update_frequency": "daily",
        "forecast_length_hours": null
      }
    ],
    "variables": [
      {
        "native_name": "SST",
        "cf_standard_name": "sea_surface_temperature",
        "long_name": "Sea Surface Temperature",
        "unit": "degC",
        "physical_quantity": "temperature",
        "thermodynamic_form": "not_applicable",
        "framework": null,
        "reference_pressure_dbar": null,
        "category": "ocean_physics",
        "is_3d": false,
        "is_vector_component": false,
        "vector_pair": null
      }
    ],
    "grid": {
      "grid_type": "regular_latlon",
      "horizontal_resolution": "0.25deg",
      "crs": "EPSG:4326",
      "coverage": {
        "lon_min": -180,
        "lon_max": 180,
        "lat_min": -90,
        "lat_max": 90
      }
    },
    "vertical": {
      "vertical_type": "surface_only",
      "n_levels": null,
      "depth_min_m": null,
      "depth_max_m": null
    },
    "access": [
      {
        "protocol": "cmems_api",
        "format": "netcdf4",
        "auth_required": true
      }
    ]
  },
  "classification_error": null
}