{
  "doc_id": "458a0d512ad754df",
  "legacy_doc_id": "403a6747383d",
  "filename": "IFS_CY48R1_Part-I_Observations.pdf",
  "filepath": "docs/ecmwf_docs/IFS_CY48R1_Part-I_Observations.pdf",
  "extension": ".pdf",
  "file_size_mb": 1.24,
  "pages": 88,
  "text_preview": "Part I: Observations\nIFS DOCUMENTATION – Cy48r1\nOperational implementation 27 June 2023\nPART I: OBSERV ATIONS\n© Copyright 2020-\nEuropean Centre for Medium-Range Weather Forecasts\nShinfield Park, Reading, RG2 9AX, UK\nThe content of this document is available for use under a Creative Commons Attribution 4.0 International\nPublic License. See the terms at https://creativecommons.org/licenses/by/4.0.\nIFS Documentation – Cy48r1 1\nREVISION HISTORY\nChanges since CY43R1\n• Minor change to text in subsection ’Conventional observations’.\n• New subsection on ’Additional error inflation for dropsondes’.\nChanges since CY41R2\n• Major rewrite and restructure of the observation documentation reflecting OOPS developments\nfor CY43R1, removal of outdated material and identification of deprecated areas of code.\n2 IFS Documentation – Cy48r1\nPart I: Observations\nChapter 1\nOverview: the observation world\nTable of contents\n1.1 Introduction\n1.2 Concepts\n1.2.1 Observation groupings, reports and datums\n1.2.2 Observation sets\n1.2.3 Timeslots\n1.2.4 Events and status\n1.2.5 The screening trajectory\n1.2.6 Observation Database usage in IFS\n1.2.7 Parallel aspects (scalability)\n1.3 Dataflow through processing and screening\n1.4 Observation groupings in the IFS\n1.4.1 Obstype and codetype\n1.4.2 SQNO - [DEPRECATED]\n1.4.3 Physical variable: varno\n1.4.4 Observation operator codes: NVAR\n1.4.5 Satgrp table and friends\n1.4.6 ‘Area’ type - [DEPRECATED]\n1.4.7 VarBC bias groups\n1.1 INTRODUCTION\nThe handling of observations is one of the most complex parts of the IFS data assimilation system.\nObservations come in diverse forms and, depending on their type, they are treated in very different\nways. The observations themselves ( y) and the observation operator H(), which converts from\nthe model state x to an observation equivalent H(x), are just part of a wider infrastructure of\nprocessing, quality control, thinning, and assigning observation errors. The metadata associated with\neach observation can run into hundreds of variables, all needing to be stored in an observation database\n(ODB). Thus the observation world encompasses:\n• Observation operators as described in Chapter 3. The input to the observation operator is\nthe ODB, plus the the model state at observation locations. Observation operators, as well\nas generating H(x), may put additional information into the ODB in some cases including\nobservation error and quality control decisions.\n• Model state interpolated to observation location or GOM PLUS is described in Part 2 (Data\nAssimilation). This contains vertical profiles of atmospheric variables (temperature, humidity etc.),\nsurface variables and any other information required from the model. Using the ‘2D GOM’ facility,\ninstead of a single vertical profile, the GOM PLUS can contain a slant-path, a set of profiles along\na limb path (e.g. for GPSRO) or just all the nearby model columns (which is used in the Bayesian\nradar retrieval at M´et´eo-France).\n• ODB is a collection of data formats and metadata describing the observations.\nIFS Documentation – Cy48r1 3\nChapter 1: Overview: the observation world\n– In the core of the IFS, processing is based on ODB-1, a hierarchical table format capable\nof running in a parallel environment, manipulated and accessed using Structured Query\nLanguage (SQL). Documentation on ODB-1 can be found at https://confluence.ecmwf.\nint/display/ODB/ODB+User+Guide.\n– However, most interactions with ODB in the IFS use an additional layer of code known as\nODB-IFS which is in the process of being completely rewritten. See Sec. 1.2.6.\n– For some pre-processing, and for archiving to MARS, the ODB-2 format is used: https:\n//confluence.ecmwf.int/display/ODBAPI.\n– The variables and codes used in the ODB are governed by a committee, and can be browsed\nat http://apps.ecmwf.int/odbgov.\n– At a more detailed level, some parts of the ODB contents are described in the current\ndocumentation, mainly in Chapter 6.\n• Observation processing is a chain that leads from the ingestion of raw data (as BUFR files and\nother data formats) to the archiving of ODBs in MARS containing diagnostics from the assimilation\nrun (traditionally known as feedback files). Apart from running the observation operators in the\ndata assimilation, observation processing has two main components that can be described as\n‘preparation’ and ‘screening’, described next.\n• Preparation generates all the parameters needed to run the observation operator in the\nassimilation system. This is everything from format conversions (e.g. BUFR to ODB-1) to the\nretrieval of surface emissivities or cloud top pressure from satellite radiances. It is also necessary\nto apply coordinate transforms (for example from windspeed and direction to horizontal wind\ncomponents) or to run a retrieval prior to assimilation (for example from backscatter to ocean\nsurface wind). This stage may include simple thinning (such as discarding some satellite\nobservations) This stage also sets up observation errors and other",
  "extraction_method": "pypdf",
  "extraction_error": null,
  "catalog_entry": null,
  "classification_error": null
}